Metadata-Version: 2.1
Name: eGUI
Version: 0.0.5
Summary: 基于Python的GUI界面，函数使用中文命名，使用简单，界面丰富，上手方便，持续更新。
Home-page: https://space.bilibili.com/365335499
Author: Python生态
Author-email: 3157024351@qq.com
License: MIT License
Keywords: Python
Platform: UNKNOWN
